{
  "home": "হোম",
  "services": "সেবা",
  "about": "আমাদের সম্পর্কে",
  "contact": "যোগাযোগ",
  "updateUser": "ব্যবহারকারী আপডেট করুন",
  "becomeHost": "হোস্ট হোন",
  "dashboard": "ড্যাশবোর্ড",
  "logout": "লগ আউট",
  "rentalheading": "আমরা কেবল মাত্র",
  "rentalheading2":"একটি গাড়ি ভাড়া কোম্পানি নই",
  "renatalsubheading": "আরবানড্রাইভ ওয়েবসাইটটি কোম্পানির মূল বার্তাটি তুলে ধরে, এটি কেবল একটি মানক গাড়ি ভাড়া পরিষেবা নয়। শিরোনামটি আরবানড্রাইভকে একটি অনন্য ব্র্যান্ড হিসাবে উপস্থাপন করে, একটি উন্নত অভিজ্ঞতা প্রদানের ধারণাকে কেন্দ্র করে।",
  "feature1": "স্পোর্টস এবং বিলাসবহুল গাড়ি",
  "feature2": "ইকোনমি গাড়ি",
  "readMore": "আরও পড়ুন",
  "rentNow": "এখন ভাড়া করুন",
  "bookAutoRental": "অটো ভাড়া বুক করুন",
  "chooseCarType": "গাড়ির ধরন নির্বাচন করুন",
  "economyCars": "ইকোনমি গাড়ি",
  "luxuryCars": "লাক্সারি গাড়ি",
  "sedan": "সেডান",
  "pickupLocation": "পিক আপ স্থান",
  "uttora": "উত্তরা",
  "mirpur1": "মিরপুর-১",
  "saver": "সাভার",
  "ajimpur": "আজিমপুর",
  "mirpur2": "মিরপুর-২",
  "pickupDate": "পিক আপ তারিখ",
  "dropOffLocation": "ড্রপ অফ স্থান",
  "returnDate": "ফেরার তারিখ",
  "rentNowButton": "এখন ভাড়া করুন",
  "Dhaka": "ঢাকা",
  "Chittagong": "চট্টগ্রাম",
  "Rajshahi": "রাজশাহী",
  "Rongpur": "রংপুর",
  "Sylhet": "সিলেট",
  "Mymensingh": "ময়মনসিংহ",
  "browseByDestination" :"গন্তব্য অনুযায়ী ব্রাউজ করুন",
  "browseByCar" : "গাড়ি অনুযায়ী ব্রাউজ করুন",
  "toyota" :"টয়োটা",
  "honda" : "হোন্ডা",
  "nissan": "নিসান",
  "suzuki": "সুজুকি",
  "reviewTitle": "ক্লায়েন্টরা কি বলছেন",
  "reviewDescription": "ক্লায়েন্টদের পর্যালোচনা UrbanDrive-কে আরও ভালো এবং কার্যকর পরিষেবা প্রদান করতে উদ্বুদ্ধ করে।",
  "name" :"নাম",
  "clientSay": "ক্লায়েন্টের মতামত",
  "newsletter": "আপডেট পেতে আমাদের নিউজলেটার সাবস্ক্রাইব করুন।",
  "welcome": "আর্থবান ড্রাইভে স্বাগতম।",
  "flexible_rental": "নমনীয় ভাড়ার পরিকল্পনা।",
  "seamless_booking": "মসৃণ বুকিং প্রক্রিয়া।",
  "ready_to_drive": "স্টাইলে ড্রাইভ করতে প্রস্তুত?",
  "about_urban_drive": "UrbanDrive সম্পর্কে",
  "our_mission": "আমাদের মিশন UrbanDrive।",
  "discover_standard": "UrbanDrive দিয়ে গাড়ি ভাড়ায় একটি নতুন মান আবিষ্কার করুন।",
  "explore_fleet": "আমাদের বহর অন্বেষণ করুন।",
  "premium_rentals": "প্রিমিয়াম গাড়ি ভাড়া।",
  "flexible_options": "নমনীয় ভাড়া বিকল্পগুলি।",
  "customer_support": "২৪/৭ গ্রাহক সহায়তা।",
  "contact_us": "আমাদের সাথে যোগাযোগ করুন",
  "phone": "+৮৮০১৮৪৯৩১৭৩৮৮",
  "email": "info@urbandrive.com",
  "location": "ঢাকা, বাংলাদেশ।",
  "copyright": "© UrbanDrive ২০২৪। সর্বস্বত্ব সংরক্ষিত।",
  "sign_in": "এখন সাইন ইন করুন"
}